pde_fncsf_exporter/__init__.py
pde_fncsf_exporter/__main__.py
pde_fncsf_exporter/__version__.py
pde_fncsf_exporter/api/__init__.py
pde_fncsf_exporter/api/cli.py
pde_fncsf_exporter/api/credentials.py
pde_fncsf_exporter/errors.py
pde_fncsf_exporter/interactor/__init__.py
pde_fncsf_exporter/interactor/validator/__init__.py
pde_fncsf_exporter/interactor/validator/parser.py
pde_fncsf_exporter/interactor/validator/rules.py
pde_fncsf_exporter/interactor/validator/targets.yml
pde_fncsf_exporter/interactor/validator/uploader.py
pde_fncsf_exporter/interactor/validator/validator.py
pde_fncsf_exporter/logger.py
pde_fncsf_exporter-0.0.7.dist-info/entry_points.txt
pde_fncsf_exporter-0.0.7.dist-info/WHEEL
pde_fncsf_exporter-0.0.7.dist-info/METADATA
pde_fncsf_exporter-0.0.7.dist-info/RECORD
